skullite/__init__.py
skullite/skullite.py
skullite-0.1.0.1.dist-info/METADATA
skullite-0.1.0.1.dist-info/WHEEL
skullite-0.1.0.1.dist-info/RECORD
