Metadata-Version: 2.4
Name: skullite
Version: 0.1.0.1
Summary: Simple SQLite high-level helper class
Project-URL: Repository, https://github.com/ductorex/skullite
Requires-Python: >=3.13
